httpso/__init__.py
httpso/__version__.py
httpso/binder.py
httpso/cookies.py
httpso/creator.py
httpso/executor.py
httpso/loader.py
httpso/response.py
httpso/session.py
httpso/util.py
httpso/c/__init__.py
httpso-0.1.1.dist-info/LICENSE
httpso-0.1.1.dist-info/METADATA
httpso-0.1.1.dist-info/WHEEL
httpso-0.1.1.dist-info/top_level.txt
httpso-0.1.1.dist-info/RECORD
